README.md
setup.py
QuickHand/__init__.py
QuickHand/database.db
QuickHand/icon.ico
QuickHand/style.css
QuickHand.egg-info/PKG-INFO
QuickHand.egg-info/SOURCES.txt
QuickHand.egg-info/dependency_links.txt
QuickHand.egg-info/entry_points.txt
QuickHand.egg-info/requires.txt
QuickHand.egg-info/top_level.txt
QuickHand/backgrounds/letter.png
QuickHand/fonts/品如手写体.ttf
QuickHand/fonts/手书体.ttf
QuickHand/fonts/杨任东竹石体.ttf
QuickHand/fonts/沐滛软书体.ttf
QuickHand/fonts/沐滛随心手写体.ttf
QuickHand/fonts/贤二体.ttf
QuickHand/fonts/阿朱泡泡体.ttf
QuickHand/fonts/青松手书体.ttf
QuickHand/fonts/青松手书体2.ttf
QuickHand/fonts/鸿雷板书简体.ttf
QuickHand/misc/README_zh.html
QuickHand/misc/assets/icon.ico
QuickHand/misc/assets/image-20200808220817456.png
QuickHand/misc/assets/params_visualizing.png
QuickHand/misc/assets/sponsor.jpg
QuickHand/moduels/ColorLabel.py
QuickHand/moduels/ConfigTab.py
QuickHand/moduels/ConsolePrintBox.py
QuickHand/moduels/ConsoleWindow.py
QuickHand/moduels/GenerateImagesThread.py
QuickHand/moduels/HandRightTab.py
QuickHand/moduels/HelpTab.py
QuickHand/moduels/SponsorDialog.py
QuickHand/moduels/SystemTray.py
QuickHand/backgrounds/letter.png
QuickHand/fonts/阿朱泡泡体.ttf
QuickHand/misc/README_zh.html
QuickHand/misc/assets/icon.ico
QuickHand/misc/assets/image-20200808220817456.png
QuickHand/misc/assets/params_visualizing.png
QuickHand/misc/assets/sponsor.jpg
QuickHand/moduels/ColorLabel.py
QuickHand/moduels/ConfigTab.py
QuickHand/moduels/ConsolePrintBox.py
QuickHand/moduels/ConsoleWindow.py
QuickHand/moduels/GenerateImagesThread.py
QuickHand/moduels/HandRightTab.py
QuickHand/moduels/HelpTab.py
QuickHand/moduels/SponsorDialog.py
QuickHand/moduels/SystemTray.py