Metadata-Version: 2.1
Name: QuickHand
Version: 1.0.4.post3
Summary: A  Chinese handwright image generater, a GUI based on  https://github.com/Gsllchb/Handright/ 
Home-page: https://github.com/HaujetZhao/QuickHand
Author: Haujet Zhao
Author-email: 1292756898@qq.com
Maintainer: Haujet Zhao
Maintainer-email: 1292756898@qq.com
License: MPL-2.0 License
Platform: all
Classifier: Development Status :: 4 - Beta
Classifier: Intended Audience :: End Users/Desktop
Classifier: Topic :: Artistic Software
Classifier: License :: OSI Approved :: Mozilla Public License 2.0 (MPL 2.0)
Classifier: Programming Language :: Python :: 3
Classifier: Programming Language :: Python :: 3.5
Classifier: Programming Language :: Python :: 3.6
Classifier: Programming Language :: Python :: 3.7
Classifier: Programming Language :: Python :: 3.8
Classifier: Programming Language :: Python :: 3 :: Only
Requires-Python: >=3.5, <4
